identicon.py
setup.py
identicon.egg-info/PKG-INFO
identicon.egg-info/SOURCES.txt
identicon.egg-info/dependency_links.txt
identicon.egg-info/pbr.json
identicon.egg-info/requires.txt
identicon.egg-info/top_level.txt