Metadata-Version: 1.0
Name: identicon
Version: 1.0
Summary: identicon python implementation
Home-page: https://github.com/shnjp/identicon
Author: Shin Adachi
Author-email: shn@glucose.jp
License: BSD
Platform: UNKNOWN
